dataset_translator-0.2.0.data/data/share/man/man1/dataset-translator.1
src/__init__.py
src/main.py
dataset_translator-0.2.0.dist-info/METADATA
dataset_translator-0.2.0.dist-info/WHEEL
dataset_translator-0.2.0.dist-info/entry_points.txt
dataset_translator-0.2.0.dist-info/top_level.txt
dataset_translator-0.2.0.dist-info/RECORD
