Metadata-Version: 2.4
Name: dataset-translator
Version: 0.2.0
Summary: ⚡️ Efficient dataset translation using Google Translate's API
Author-email: Iván Moreno <ivan@ivan.build>
License: MIT
Project-URL: Repository, https://github.com/ivanvmoreno/dataset-translator
Project-URL: Issues, https://github.com/ivanvmoreno/dataset-translator/issues
Keywords: dataset,translate,hf,google,api
Classifier: Programming Language :: Python :: 3
Classifier: Programming Language :: Python :: 3.8
Classifier: Programming Language :: Python :: 3.9
Classifier: Programming Language :: Python :: 3.10
Classifier: Programming Language :: Python :: 3.11
Classifier: Programming Language :: Python :: 3.12
Classifier: Programming Language :: Python :: 3.13
Classifier: Programming Language :: Python :: 3.14
Requires-Python: >=3.8
Requires-Dist: datasets
Requires-Dist: google-cloud-translate>=3.23.0
Requires-Dist: googletrans
Requires-Dist: jsonlines>=4.0.0
Requires-Dist: pandas
Requires-Dist: pyarrow
Requires-Dist: tqdm
Requires-Dist: typer
